yaml_env_var_parser/__init__.py
yaml_env_var_parser/yaml_env_var_parser.py
yaml_env_var_parser-1.1.1.dist-info/LICENSE
yaml_env_var_parser-1.1.1.dist-info/METADATA
yaml_env_var_parser-1.1.1.dist-info/WHEEL
yaml_env_var_parser-1.1.1.dist-info/top_level.txt
yaml_env_var_parser-1.1.1.dist-info/RECORD
