Metadata-Version: 2.1
Name: yaml-env-var-parser
Version: 1.1.1
Summary: Implementation of PyYAML Reader with environment variables parsing.
Home-page: https://github.com/NiltonDuarte/yaml_env_var_parser
Author: Nilton Duarte
Author-email: github@niltonduarte.com
License: MIT
Keywords: YAML,environ,environment variables,parsing
Platform: any
Classifier: Operating System :: OS Independent
Classifier: License :: OSI Approved :: MIT License
Classifier: Topic :: Utilities
Classifier: Intended Audience :: Developers
Classifier: Topic :: Software Development :: Libraries :: Python Modules
Classifier: Programming Language :: Python :: 3.6
Classifier: Programming Language :: Python :: 3.7
Classifier: Programming Language :: Python :: 3.8
Classifier: Programming Language :: Python :: 3.9
Classifier: Programming Language :: Python :: 3.10
Requires-Python: >=3.6
License-File: LICENSE
Requires-Dist: PyYAML
